loducode_web3/__init__.py
loducode_web3/apps.py
loducode_web3/tests.py
loducode_web3/utils.py
loducode_web3/views.py
loducode_web3/helpers/__init__.py
loducode_web3/helpers/contract_nfts.py
loducode_web3/helpers/wallet.py
loducode_web3/locale/__init__.py
loducode_web3/management/__init__.py
loducode_web3/managers/__init__.py
loducode_web3/managers/attribute_nft_manager.py
loducode_web3/managers/nft_manager.py
loducode_web3/migrations/__init__.py
loducode_web3/models/__init__.py
loducode_web3/models/attribute_nft.py
loducode_web3/models/nft.py
loducode_web3-0.1.15.dist-info/LICENSE.txt
loducode_web3-0.1.15.dist-info/METADATA
loducode_web3-0.1.15.dist-info/WHEEL
loducode_web3-0.1.15.dist-info/top_level.txt
loducode_web3-0.1.15.dist-info/RECORD
