Metadata-Version: 2.1
Name: loducode_web3
Version: 0.1.15
Summary: Basic components for the development of loducode s.a.s. for web3
Home-page: https://github.com/cristdulcey/loducode_web3.git
Download-URL: https://github.com/cristdulcey/loducode_web3.git/tarball/master
Author: Cristian Dulcey
Author-email: cristian@loducode.com
Keywords: web3,loducode_web3,loducode
License-File: LICENSE.txt
Requires-Dist: markdown >=3.2.2
Requires-Dist: MarkupPy >=1.14
Requires-Dist: MarkupSafe >=1.1.1
Requires-Dist: djangorestframework >=3.11.2
Requires-Dist: django-filter >=2.2.0
Requires-Dist: django-rest-swagger >=2.2.0
Requires-Dist: django >=3.0
Requires-Dist: django-crum >=0.7.5
Requires-Dist: django-import-export >=2.1.0
Requires-Dist: loducode-utils >=1.5.1
Requires-Dist: web3 >=6.19.0
